MANIFEST.in
README
setup.py
tox.ini
cubicweb_awstats/__init__.py
cubicweb_awstats/__pkginfo__.py
cubicweb_awstats/ccplugin.py
cubicweb_awstats/entities.py
cubicweb_awstats/hooks.py
cubicweb_awstats/schema.py
cubicweb_awstats/site_cubicweb.py
cubicweb_awstats/utils.py
cubicweb_awstats.egg-info/PKG-INFO
cubicweb_awstats.egg-info/SOURCES.txt
cubicweb_awstats.egg-info/dependency_links.txt
cubicweb_awstats.egg-info/entry_points.txt
cubicweb_awstats.egg-info/not-zip-safe
cubicweb_awstats.egg-info/requires.txt
cubicweb_awstats.egg-info/top_level.txt
cubicweb_awstats/data/cubes.awstats.js
cubicweb_awstats/i18n/de.po
cubicweb_awstats/i18n/en.po
cubicweb_awstats/i18n/es.po
cubicweb_awstats/i18n/fr.po
cubicweb_awstats/views/__init__.py
cubicweb_awstats/views/actions.py
cubicweb_awstats/views/primary.py
cubicweb_awstats/views/startup.py
test/test_awstats.py
test/test_compress.py