Metadata-Version: 1.1
Name: cubicweb-awstats
Version: 0.3.0
Summary: cubicweb integrated awstats frontend
Home-page: https://www.cubicweb.org/project/cubicweb-awstats
Author: LOGILAB S.A. (Paris, FRANCE)
Author-email: contact@logilab.fr
License: LGPL
Platform: UNKNOWN
Classifier: Environment :: Web Environment
Classifier: Framework :: CubicWeb
Classifier: Programming Language :: Python
Classifier: Programming Language :: JavaScript
